efb_gpg_middleware/__init__.py
efb_gpg_middleware/__version__.py
efb_gpg_middleware/locale/az_AZ/LC_MESSAGES/efb_gpg_middleware.mo
efb_gpg_middleware/locale/az_AZ/LC_MESSAGES/efb_gpg_middleware.po
efb_gpg_middleware/locale/en_US/LC_MESSAGES/efb_gpg_middleware.mo
efb_gpg_middleware/locale/en_US/LC_MESSAGES/efb_gpg_middleware.po
efb_gpg_middleware/locale/es_AR/LC_MESSAGES/efb_gpg_middleware.po
efb_gpg_middleware/locale/es_VE/LC_MESSAGES/efb_gpg_middleware.mo
efb_gpg_middleware/locale/es_VE/LC_MESSAGES/efb_gpg_middleware.po
efb_gpg_middleware/locale/id_ID/LC_MESSAGES/efb_gpg_middleware.mo
efb_gpg_middleware/locale/id_ID/LC_MESSAGES/efb_gpg_middleware.po
efb_gpg_middleware/locale/it_IT/LC_MESSAGES/efb_gpg_middleware.po
efb_gpg_middleware/locale/ja_JP/LC_MESSAGES/efb_gpg_middleware.mo
efb_gpg_middleware/locale/ja_JP/LC_MESSAGES/efb_gpg_middleware.po
efb_gpg_middleware/locale/ms_MY/LC_MESSAGES/efb_gpg_middleware.mo
efb_gpg_middleware/locale/ms_MY/LC_MESSAGES/efb_gpg_middleware.po
efb_gpg_middleware/locale/ro_RO/LC_MESSAGES/efb_gpg_middleware.po
efb_gpg_middleware/locale/tr_TR/LC_MESSAGES/efb_gpg_middleware.mo
efb_gpg_middleware/locale/tr_TR/LC_MESSAGES/efb_gpg_middleware.po
efb_gpg_middleware/locale/zh_CN/LC_MESSAGES/efb_gpg_middleware.mo
efb_gpg_middleware/locale/zh_CN/LC_MESSAGES/efb_gpg_middleware.po
efb_gpg_middleware/locale/zh_TW/LC_MESSAGES/efb_gpg_middleware.mo
efb_gpg_middleware/locale/zh_TW/LC_MESSAGES/efb_gpg_middleware.po
efb_gpg_middleware-1.1.1.dist-info/LICENSE.md
efb_gpg_middleware-1.1.1.dist-info/METADATA
efb_gpg_middleware-1.1.1.dist-info/WHEEL
efb_gpg_middleware-1.1.1.dist-info/entry_points.txt
efb_gpg_middleware-1.1.1.dist-info/top_level.txt
efb_gpg_middleware-1.1.1.dist-info/RECORD
