Metadata-Version: 2.1
Name: efb-gpg-middleware
Version: 1.1.1
Summary: GPG middleware for EH Forwarder Bot, encrypts and decrypts messages.
Home-page: https://github.com/ehForwarderBot/efb-gpg-middleware
Author: Eana Hufwe
Author-email: ilove@1a23.com
License: AGPLv3+
Keywords: ehforwarderbot,EH Forwarder Bot,EH Forwarder Bot Master Channel,PGP,GPG,GnuPG
Platform: UNKNOWN
Classifier: Development Status :: 4 - Beta
Classifier: License :: OSI Approved :: GNU Affero General Public License v3 or later (AGPLv3+)
Classifier: Intended Audience :: Developers
Classifier: Intended Audience :: End Users/Desktop
Classifier: Programming Language :: Python :: 3 :: Only
Classifier: Programming Language :: Python :: 3.6
Classifier: Programming Language :: Python :: 3.7
Classifier: Programming Language :: Python :: 3.8
Classifier: Topic :: Communications :: Chat
Classifier: Topic :: Utilities
Requires-Python: >=3.6
Requires-Dist: ehforwarderbot (>=2.0.0)
Requires-Dist: python-gnupg
